hermessplitter/__init__.py
hermessplitter/functions.py
hermessplitter/main.py
hermessplitter/db/__init__.py
hermessplitter/db/db_funcs.py
hermessplitter/db/init_db.py
hermessplitter/db/tables.py
hermessplitter/db/tests/__init__.py
hermessplitter/db/tests/db_funcs_test.py
hermessplitter/tests/__init__.py
hermessplitter/tests/hermes_activate_tests.py
hermessplitter/tests/test_functions.py
hermessplitter_ws_one-0.0.2.dist-info/LICENSE
hermessplitter_ws_one-0.0.2.dist-info/METADATA
hermessplitter_ws_one-0.0.2.dist-info/WHEEL
hermessplitter_ws_one-0.0.2.dist-info/top_level.txt
hermessplitter_ws_one-0.0.2.dist-info/RECORD
