Metadata-Version: 2.1
Name: hermessplitter-ws-one
Version: 0.0.2
Summary: UNKNOWN
Author: punchyarchy
Author-email: ksmdrmvscthny@gmail.com
License: UNKNOWN
Platform: UNKNOWN
License-File: LICENSE
